aliyunsdkbrain_industrial/__init__.py
aliyunsdkbrain_industrial/endpoint.py
aliyunsdkbrain_industrial/request/__init__.py
aliyunsdkbrain_industrial/request/v20200920/ActivateLicenseRequest.py
aliyunsdkbrain_industrial/request/v20200920/AicsOpenApiInvokeRequest.py
aliyunsdkbrain_industrial/request/v20200920/CreateEssOptJobRequest.py
aliyunsdkbrain_industrial/request/v20200920/CreateLoadForecastJobRequest.py
aliyunsdkbrain_industrial/request/v20200920/CreatePowerForecastJobRequest.py
aliyunsdkbrain_industrial/request/v20200920/GetAivppAlgoJobRequest.py
aliyunsdkbrain_industrial/request/v20200920/GetLicenseRequest.py
aliyunsdkbrain_industrial/request/v20200920/ListAivppResourcesRequest.py
aliyunsdkbrain_industrial/request/v20200920/ListLicensesRequest.py
aliyunsdkbrain_industrial/request/v20200920/ListUserResourcesRequest.py
aliyunsdkbrain_industrial/request/v20200920/UpdateLicenseDescriptionRequest.py
aliyunsdkbrain_industrial/request/v20200920/__init__.py
aliyun_python_sdk_brain_industrial-1.0.4.dist-info/LICENSE
aliyun_python_sdk_brain_industrial-1.0.4.dist-info/METADATA
aliyun_python_sdk_brain_industrial-1.0.4.dist-info/WHEEL
aliyun_python_sdk_brain_industrial-1.0.4.dist-info/top_level.txt
aliyun_python_sdk_brain_industrial-1.0.4.dist-info/RECORD
